Workbook

Sheet Dashboard
U4: Current Year | X4: ROA = 15% | Y4: 0.15
U5: NPM | V5: TAT | X5: Step Size | Y5: 0.02
T6: A | U6: =D47 -> #DIV/0! | V6: =D54 -> #DIV/0!
T7: B | U7: =D48 -> #DIV/0! | V7: =D55 -> #DIV/0!
T8: C | U8: =D49 -> #DIV/0! | V8: =D56 -> #DIV/0! | X8: NPM | Y8: TAT
T9: D | U9: =D50 -> #DIV/0! | V9: =D57 -> #DIV/0! | X9: 0.4 | Y9: =$Y$4/X9 -> 0.375
T10: E | U10: =D51 -> #DIV/0! | V10: =D58 -> #DIV/0! | X10: =X9-$Y$5 -> 0.38 | Y10: =$Y$4/X10 -> 0.39473684
T11: F | U11: =D52 -> #DIV/0! | V11: =D59 -> #DIV/0! | X11: =X10-$Y$5 -> 0.36 | Y11: =$Y$4/X11 -> 0.41666667
T12: G | U12: =D53 -> #DIV/0! | V12: =D60 -> #DIV/0! | X12: =X11-$Y$5 -> 0.34 | Y12: =$Y$4/X12 -> 0.44117647
X13: =X12-$Y$5 -> 0.32 | Y13: =$Y$4/X13 -> 0.46875
X14: =X13-$Y$5 -> 0.3 | Y14: =$Y$4/X14 -> 0.5
X15: =X14-$Y$5 -> 0.28 | Y15: =$Y$4/X15 -> 0.53571429
X16: =X15-$Y$5 -> 0.26 | Y16: =$Y$4/X16 -> 0.57692308
X17: =X16-$Y$5 -> 0.24 | Y17: =$Y$4/X17 -> 0.625
X18: =X17-$Y$5 -> 0.22 | Y18: =$Y$4/X18 -> 0.68181818
X19: =X18-$Y$5 -> 0.2 | Y19: =$Y$4/X19 -> 0.75
X20: =X19-$Y$5 -> 0.18 | Y20: =$Y$4/X20 -> 0.83333333
X21: =X20-$Y$5 -> 0.16 | Y21: =$Y$4/X21 -> 0.9375
X22: =X21-$Y$5 -> 0.14 | Y22: =$Y$4/X22 -> 1.0714286
X23: =X22-$Y$5 -> 0.12 | Y23: =$Y$4/X23 -> 1.25
X24: =X23-$Y$5 -> 0.1 | Y24: =$Y$4/X24 -> 1.5
... X28: =X27-$Y$5 -> 0.02 | Y28: =$Y$4/X28 -> 7.5
A46: Industry | B46: Measure | C46: Firm | D46: Year 1 | E46: Year 2 | F46: Year 3 | G46: Year 4 | H46: Year 5 | I46: Year 6 | J46: Year 7 | K46: Year 8
A47: Section 1 | B47: Net Profit Margin | C47: A | D47: ='Year 1'!$D$44 -> #DIV/0! | E47: ='Year 2'!$D$44 -> #DIV/0! | F47: ='Year 3'!$D$44 -> #DIV/0! | G47: ='Year 4'!$D$44 -> #DIV/0! | H47: ='Year 5'!$D$44 -> #DIV/0! | I47: ='Year 6'!$D$44 -> #DIV/0! | J47: ='Year 7'!$D$44 -> #DIV/0! | K47: ='Year 8'!$D$44 -> #DIV/0!
A48: Section 1 | B48: Net Profit Margin | C48: B | D48: ='Year 1'!$E$44 -> #DIV/0! | E48: ='Year 2'!$E$44 -> #DIV/0! | F48: ='Year 3'!$E$44 -> #DIV/0! | G48: ='Year 4'!$E$44 -> #DIV/0! | H48: ='Year 5'!$E$44 -> #DIV/0! | I48: ='Year 6'!$E$44 -> #DIV/0! | J48: ='Year 7'!$E$44 -> #DIV/0! | K48: ='Year 8'!$E$44 -> #DIV/0!
A49: Section 1 | B49: Net Profit Margin | C49: C | D49: ='Year 1'!$F$44 -> #DIV/0! | E49: ='Year 2'!$F$44 -> #DIV/0! | F49: ='Year 3'!$F$44 -> #DIV/0! | G49: ='Year 4'!$F$44 -> #DIV/0! | H49: ='Year 5'!$F$44 -> #DIV/0! | I49: ='Year 6'!$F$44 -> #DIV/0! | J49: ='Year 7'!$F$44 -> #DIV/0! | K49: ='Year 8'!$F$44 -> #DIV/0!
A50: Section 1 | B50: Net Profit Margin | C50: D | D50: ='Year 1'!$G$44 -> #DIV/0! | E50: ='Year 2'!$G$44 -> #DIV/0! | F50: ='Year 3'!$G$44 -> #DIV/0! | G50: ='Year 4'!$G$44 -> #DIV/0! | H50: ='Year 5'!$G$44 -> #DIV/0! | I50: ='Year 6'!$G$44 -> #DIV/0! | J50: ='Year 7'!$G$44 -> #DIV/0! | K50: ='Year 8'!$G$44 -> #DIV/0!
A51: Section 1 | B51: Net Profit Margin | C51: E | D51: ='Year 1'!$H$44 -> #DIV/0! | E51: ='Year 2'!$H$44 -> #DIV/0! | F51: ='Year 3'!$H$44 -> #DIV/0! | G51: ='Year 4'!$H$44 -> #DIV/0! | H51: ='Year 5'!$H$44 -> #DIV/0! | I51: ='Year 6'!$H$44 -> #DIV/0! | J51: ='Year 7'!$H$44 -> #DIV/0! | K51: ='Year 8'!$H$44 -> #DIV/0!
A52: Section 1 | B52: Net Profit Margin | C52: F | D52: ='Year 1'!$I$44 -> #DIV/0! | E52: ='Year 2'!$I$44 -> #DIV/0! | F52: ='Year 3'!$I$44 -> #DIV/0! | G52: ='Year 4'!$I$44 -> #DIV/0! | H52: ='Year 5'!$I$44 -> #DIV/0! | I52: ='Year 6'!$I$44 -> #DIV/0! | J52: ='Year 7'!$I$44 -> #DIV/0! | K52: ='Year 8'!$I$44 -> #DIV/0!
A53: Section 1 | B53: Net Profit Margin | C53: G | D53: ='Year 1'!$J$44 -> #DIV/0! | E53: ='Year 2'!$J$44 -> #DIV/0! | F53: ='Year 3'!$J$44 -> #DIV/0! | G53: ='Year 4'!$J$44 -> #DIV/0! | H53: ='Year 5'!$J$44 -> #DIV/0! | I53: ='Year 6'!$J$44 -> #DIV/0! | J53: ='Year 7'!$J$44 -> #DIV/0! | K53: ='Year 8'!$J$44 -> #DIV/0!
A54: Section 1 | B54: Total Asset Turnover | C54: A | D54: ='Year 1'!$D$57 -> #DIV/0! | E54: ='Year 2'!$D$57 -> #DIV/0! | F54: ='Year 3'!$D$57 -> #DIV/0! | G54: ='Year 4'!$D$57 -> #DIV/0! | H54: ='Year 5'!$D$57 -> #DIV/0! | I54: ='Year 6'!$D$57 -> #DIV/0! | J54: ='Year 7'!$D$57 -> #DIV/0! | K54: ='Year 8'!$D$57 -> #DIV/0!
A55: Section 1 | B55: Total Asset Turnover | C55: B | D55: ='Year 1'!$E$57 -> #DIV/0! | E55: ='Year 2'!$E$57 -> #DIV/0! | F55: ='Year 3'!$E$57 -> #DIV/0! | G55: ='Year 4'!$E$57 -> #DIV/0! | H55: ='Year 5'!$E$57 -> #DIV/0! | I55: ='Year 6'!$E$57 -> #DIV/0! | J55: ='Year 7'!$E$57 -> #DIV/0! | K55: ='Year 8'!$E$57 -> #DIV/0!
A56: Section 1 | B56: Total Asset Turnover | C56: C | D56: ='Year 1'!$F$57 -> #DIV/0! | E56: ='Year 2'!$F$57 -> #DIV/0! | F56: ='Year 3'!$F$57 -> #DIV/0! | G56: ='Year 4'!$F$57 -> #DIV/0! | H56: ='Year 5'!$F$57 -> #DIV/0! | I56: ='Year 6'!$F$57 -> #DIV/0! | J56: ='Year 7'!$F$57 -> #DIV/0! | K56: ='Year 8'!$F$57 -> #DIV/0!
A57: Section 1 | B57: Total Asset Turnover | C57: D | D57: ='Year 1'!$G$57 -> #DIV/0! | E57: ='Year 2'!$G$57 -> #DIV/0! | F57: ='Year 3'!$G$57 -> #DIV/0! | G57: ='Year 4'!$G$57 -> #DIV/0! | H57: ='Year 5'!$G$57 -> #DIV/0! | I57: ='Year 6'!$G$57 -> #DIV/0! | J57: ='Year 7'!$G$57 -> #DIV/0! | K57: ='Year 8'!$G$57 -> #DIV/0!
A58: Section 1 | B58: Total Asset Turnover | C58: E | D58: ='Year 1'!$H$57 -> #DIV/0! | E58: ='Year 2'!$H$57 -> #DIV/0! | F58: ='Year 3'!$H$57 -> #DIV/0! | G58: ='Year 4'!$H$57 -> #DIV/0! | H58: ='Year 5'!$H$57 -> #DIV/0! | I58: ='Year 6'!$H$57 -> #DIV/0! | J58: ='Year 7'!$H$57 -> #DIV/0! | K58: ='Year 8'!$H$57 -> #DIV/0!
A59: Section 1 | B59: Total Asset Turnover | C59: F | D59: ='Year 1'!$I$57 -> #DIV/0! | E59: ='Year 2'!$I$57 -> #DIV/0! | F59: ='Year 3'!$I$57 -> #DIV/0! | G59: ='Year 4'!$I$57 -> #DIV/0! | H59: ='Year 5'!$I$57 -> #DIV/0! | I59: ='Year 6'!$I$57 -> #DIV/0! | J59: ='Year 7'!$I$57 -> #DIV/0! | K59: ='Year 8'!$I$57 -> #DIV/0!
A60: Section 1 | B60: Total Asset Turnover | C60: G | D60: ='Year 1'!$J$57 -> #DIV/0! | E60: ='Year 2'!$J$57 -> #DIV/0! | F60: ='Year 3'!$J$57 -> #DIV/0! | G60: ='Year 4'!$J$57 -> #DIV/0! | H60: ='Year 5'!$J$57 -> #DIV/0! | I60: ='Year 6'!$J$57 -> #DIV/0! | J60: ='Year 7'!$J$57 -> #DIV/0! | K60: ='Year 8'!$J$57 -> #DIV/0!
A61: Section 1 | B61: Equity Multiplier | C61: A | D61: ='Year 1'!$D$48 -> #DIV/0! | E61: ='Year 2'!$D$48 -> #DIV/0! | F61: ='Year 3'!$D$48 -> #DIV/0! | G61: ='Year 4'!$D$48 -> #DIV/0! | H61: ='Year 5'!$D$48 -> #DIV/0! | I61: ='Year 6'!$D$48 -> #DIV/0! | J61: ='Year 7'!$D$48 -> #DIV/0! | K61: ='Year 8'!$D$48 -> #DIV/0!
A62: Section 1 | B62: Equity Multiplier | C62: B | D62: ='Year 1'!$E$48 -> #DIV/0! | E62: ='Year 2'!$E$48 -> #DIV/0! | F62: ='Year 3'!$E$48 -> #DIV/0! | G62: ='Year 4'!$E$48 -> #DIV/0! | H62: ='Year 5'!$E$48 -> #DIV/0! | I62: ='Year 6'!$E$48 -> #DIV/0! | J62: ='Year 7'!$E$48 -> #DIV/0! | K62: ='Year 8'!$E$48 -> #DIV/0!
A63: Section 1 | B63: Equity Multiplier | C63: C | D63: ='Year 1'!$F$48 -> #DIV/0! | E63: ='Year 2'!$F$48 -> #DIV/0! | F63: ='Year 3'!$F$48 -> #DIV/0! | G63: ='Year 4'!$F$48 -> #DIV/0! | H63: ='Year 5'!$F$48 -> #DIV/0! | I63: ='Year 6'!$F$48 -> #DIV/0! | J63: ='Year 7'!$F$48 -> #DIV/0! | K63: ='Year 8'!$F$48 -> #DIV/0!
A64: Section 1 | B64: Equity Multiplier | C64: D | D64: ='Year 1'!$G$48 -> #DIV/0! | E64: ='Year 2'!$G$48 -> #DIV/0! | F64: ='Year 3'!$G$48 -> #DIV/0! | G64: ='Year 4'!$G$48 -> #DIV/0! | H64: ='Year 5'!$G$48 -> #DIV/0! | I64: ='Year 6'!$G$48 -> #DIV/0! | J64: ='Year 7'!$G$48 -> #DIV/0! | K64: ='Year 8'!$G$48 -> #DIV/0!
A65: Section 1 | B65: Equity Multiplier | C65: E | D65: ='Year 1'!$H$48 -> #DIV/0! | E65: ='Year 2'!$H$48 -> #DIV/0! | F65: ='Year 3'!$H$48 -> #DIV/0! | G65: ='Year 4'!$H$48 -> #DIV/0! | H65: ='Year 5'!$H$48 -> #DIV/0! | I65: ='Year 6'!$H$48 -> #DIV/0! | J65: ='Year 7'!$H$48 -> #DIV/0! | K65: ='Year 8'!$H$48 -> #DIV/0!
A66: Section 1 | B66: Equity Multiplier | C66: F | D66: ='Year 1'!$I$48 -> #DIV/0! | E66: ='Year 2'!$I$48 -> #DIV/0! | F66: ='Year 3'!$I$48 -> #DIV/0! | G66: ='Year 4'!$I$48 -> #DIV/0! | H66: ='Year 5'!$I$48 -> #DIV/0! | I66: ='Year 6'!$I$48 -> #DIV/0! | J66: ='Year 7'!$I$48 -> #DIV/0! | K66: ='Year 8'!$I$48 -> #DIV/0!
A67: Section 1 | B67: Equity Multiplier | C67: G | D67: ='Year 1'!$J$48 -> #DIV/0! | E67: ='Year 2'!$J$48 -> #DIV/0! | F67: ='Year 3'!$J$48 -> #DIV/0! | G67: ='Year 4'!$J$48 -> #DIV/0! | H67: ='Year 5'!$J$48 -> #DIV/0! | I67: ='Year 6'!$J$48 -> #DIV/0! | J67: ='Year 7'!$J$48 -> #DIV/0! | K67: ='Year 8'!$J$48 -> #DIV/0!
A68: Section 1 | B68: Return on Equity | C68: A | D68: ='Year 1'!$D$46 -> #DIV/0! | E68: ='Year 2'!$D$46 -> #DIV/0! | F68: ='Year 3'!$D$46 -> #DIV/0! | G68: ='Year 4'!$D$46 -> #DIV/0! | H68: ='Year 5'!$D$46 -> #DIV/0! | I68: ='Year 6'!$D$46 -> #DIV/0! | J68: ='Year 7'!$D$46 -> #DIV/0! | K68: ='Year 8'!$D$46 -> #DIV/0!
A69: Section 1 | B69: Return on Equity | C69: B | D69: ='Year 1'!$E$46 -> #DIV/0! | E69: ='Year 2'!$E$46 -> #DIV/0! | F69: ='Year 3'!$E$46 -> #DIV/0! | G69: ='Year 4'!$E$46 -> #DIV/0! | H69: ='Year 5'!$E$46 -> #DIV/0! | I69: ='Year 6'!$E$46 -> #DIV/0! | J69: ='Year 7'!$E$46 -> #DIV/0! | K69: ='Year 8'!$E$46 -> #DIV/0!
A70: Section 1 | B70: Return on Equity | C70: C | D70: ='Year 1'!$F$46 -> #DIV/0! | E70: ='Year 2'!$F$46 -> #DIV/0! | F70: ='Year 3'!$F$46 -> #DIV/0! | G70: ='Year 4'!$F$46 -> #DIV/0! | H70: ='Year 5'!$F$46 -> #DIV/0! | I70: ='Year 6'!$F$46 -> #DIV/0! | J70: ='Year 7'!$F$46 -> #DIV/0! | K70: ='Year 8'!$F$46 -> #DIV/0!
A71: Section 1 | B71: Return on Equity | C71: D | D71: ='Year 1'!$G$46 -> #DIV/0! | E71: ='Year 2'!$G$46 -> #DIV/0! | F71: ='Year 3'!$G$46 -> #DIV/0! | G71: ='Year 4'!$G$46 -> #DIV/0! | H71: ='Year 5'!$G$46 -> #DIV/0! | I71: ='Year 6'!$G$46 -> #DIV/0! | J71: ='Year 7'!$G$46 -> #DIV/0! | K71: ='Year 8'!$G$46 -> #DIV/0!
A72: Section 1 | B72: Return on Equity | C72: E | D72: ='Year 1'!$H$46 -> #DIV/0! | E72: ='Year 2'!$H$46 -> #DIV/0! | F72: ='Year 3'!$H$46 -> #DIV/0! | G72: ='Year 4'!$H$46 -> #DIV/0! | H72: ='Year 5'!$H$46 -> #DIV/0! | I72: ='Year 6'!$H$46 -> #DIV/0! | J72: ='Year 7'!$H$46 -> #DIV/0! | K72: ='Year 8'!$H$46 -> #DIV/0!
A73: Section 1 | B73: Return on Equity | C73: F | D73: ='Year 1'!$I$46 -> #DIV/0! | E73: ='Year 2'!$I$46 -> #DIV/0! | F73: ='Year 3'!$I$46 -> #DIV/0! | G73: ='Year 4'!$I$46 -> #DIV/0! | H73: ='Year 5'!$I$46 -> #DIV/0! | I73: ='Year 6'!$I$46 -> #DIV/0! | J73: ='Year 7'!$I$46 -> #DIV/0! | K73: ='Year 8'!$I$46 -> #DIV/0!
A74: Section 1 | B74: Return on Equity | C74: G | D74: ='Year 1'!#REF! -> #REF! | E74: ='Year 2'!#REF! -> #REF! | F74: ='Year 3'!#REF! -> #REF! | G74: ='Year 4'!#REF! -> #REF! | H74: ='Year 5'!#REF! -> #REF! | I74: ='Year 6'!#REF! -> #REF! | J74: ='Year 7'!#REF! -> #REF! | K74: ='Year 8'!#REF! -> #REF!
A75: Section 1 | B75: Return on Equity | C75: G | D75: ='Year 1'!$J$46 -> #DIV/0! | E75: ='Year 2'!$J$46 -> #DIV/0! | F75: ='Year 3'!$J$46 -> #DIV/0! | G75: ='Year 4'!$J$46 -> #DIV/0! | H75: ='Year 5'!$J$46 -> #DIV/0! | I75: ='Year 6'!$J$46 -> #DIV/0! | J75: ='Year 7'!$J$46 -> #DIV/0! | K75: ='Year 8'!$J$46 -> #DIV/0!

Sheet Year 1
B3: Income Statement | C3: MILLIONS | D3: FIRM A | E3: FIRM B | F3: FIRM C | G3: FIRM D | H3: FIRM E | I3: FIRM F | J3: FIRM G
C4: Sales
C5: Cost of Goods Sold
C6: Gross Margin
C7: Marketing
C8: Research and Development
C9: General and Administrative
C10: Income from Operations
C11: Interest Income
C12: Interest Expense
C13: Extraordinary Items
C14: Income before Tax
C15: Less Tax @ 35%
... C17: Dividends Paid
B18: Balance Sheet | C18: MILLIONS | D18: FIRM A | E18: FIRM B | F18: FIRM C | G18: FIRM D | H18: FIRM E | I18: FIRM F | J18: FIRM G
B19: Assets | C19: Cash
C20: Short-term securities
C21: Receivables
C22: Inventory
C23: Plant and Equipment
C24: Accumulated Depreciation
C25: Total Assets
B26: Liabilities | C26: Accounts Payable
C27: Short Term Debt
C28: Long Term Debt
C29: Total Liabilities
B30: Equity | C30: Stock ($1 par)
C31: Add'l Paid in Cap.
C32: Retained Earnings
C33: Treasury Stock
C34: Total Equity
B35: Inventory Detail | C35: Beg. Inventory
C36: End. Inventory
C37: Avg. Inventory | D37: =SUM(D35:D36)/2 -> 0 | E37: =SUM(E35:E36)/2 -> 0 | F37: =SUM(F35:F36)/2 -> 0 | G37: =SUM(G35:G36)/2 -> 0 | H37: =SUM(H35:H36)/2 -> 0 | I37: =SUM(I35:I36)/2 -> 0 | J37: =SUM(J35:J36)/2 -> 0
B38: Cash Flow | C38: MILLIONS | D38: FIRM A | E38: FIRM B | F38: FIRM C | G38: FIRM D | H38: FIRM E | I38: FIRM F | J38: FIRM G
C39: Net Cash from Operations
C40: Net investment
B41: Ratios | D41: FIRM A | E41: FIRM B | F41: FIRM C | G41: FIRM D | H41: FIRM E | I41: FIRM F | J41: FIRM G
B42: Profitability | C42: Gross Profit Margin | D42: =D6/D4 -> #DIV/0! | E42: =E6/E4 -> #DIV/0! | F42: =F6/F4 -> #DIV/0! | G42: =G6/G4 -> #DIV/0! | H42: =H6/H4 -> #DIV/0! | I42: =I6/I4 -> #DIV/0! | J42: =J6/J4 -> #DIV/0!
C43: Operating Profit Margin | D43: =D10/D4 -> #DIV/0! | E43: =E10/E4 -> #DIV/0! | F43: =F10/F4 -> #DIV/0! | G43: =G10/G4 -> #DIV/0! | H43: =H10/H4 -> #DIV/0! | I43: =I10/I4 -> #DIV/0! | J43: =J10/J4 -> #DIV/0!
C44: Net Profit Margin | D44: =D16/D4 -> #DIV/0! | E44: =E16/E4 -> #DIV/0! | F44: =F16/F4 -> #DIV/0! | G44: =G16/G4 -> #DIV/0! | H44: =H16/H4 -> #DIV/0! | I44: =I16/I4 -> #DIV/0! | J44: =J16/J4 -> #DIV/0!
C45: Return on Assets | D45: =D16/D25 -> #DIV/0! | E45: =E16/E25 -> #DIV/0! | F45: =F16/F25 -> #DIV/0! | G45: =G16/G25 -> #DIV/0! | H45: =H16/H25 -> #DIV/0! | I45: =I16/I25 -> #DIV/0! | J45: =J16/J25 -> #DIV/0!
C46: Return on Equity | D46: =IF(D34<0,"N/A",D16/D34) -> #DIV/0! | E46: =IF(E34<0,"N/A",E16/E34) -> #DIV/0! | F46: =IF(F34<0,"N/A",F16/F34) -> #DIV/0! | G46: =IF(G34<0,"N/A",G16/G34) -> #DIV/0! | H46: =IF(H34<0,"N/A",H16/H34) -> #DIV/0! | I46: =IF(I34<0,"N/A",I16/I34) -> #DIV/0! | J46: =IF(J34<0,"N/A",J16/J34) -> #DIV/0!
B47: Leverage | C47: Debt-to-Equity | D47: =D29/D34 -> #DIV/0! | E47: =E29/E34 -> #DIV/0! | F47: =F29/F34 -> #DIV/0! | G47: =G29/G34 -> #DIV/0! | H47: =H29/H34 -> #DIV/0! | I47: =I29/I34 -> #DIV/0! | J47: =J29/J34 -> #DIV/0!
C48: Equity Multiplier | D48: =D25/D34 -> #DIV/0! | E48: =E25/E34 -> #DIV/0! | F48: =F25/F34 -> #DIV/0! | G48: =G25/G34 -> #DIV/0! | H48: =H25/H34 -> #DIV/0! | I48: =I25/I34 -> #DIV/0! | J48: =J25/J34 -> #DIV/0!
C49: Interest Coverage | D49: =D10/ABS(D12) -> #DIV/0! | E49: =E10/ABS(E12) -> #DIV/0! | F49: =F10/ABS(F12) -> #DIV/0! | G49: =G10/ABS(G12) -> #DIV/0! | H49: =H10/ABS(H12) -> #DIV/0! | I49: =I10/ABS(I12) -> #DIV/0! | J49: =J10/ABS(J12) -> #DIV/0!
B50: Liquidity | C50: Current Ratio | D50: =SUM(D19:D22)/SUM(D26:D27) -> #DIV/0! | E50: =SUM(E19:E22)/SUM(E26:E27) -> #DIV/0! | F50: =SUM(F19:F22)/SUM(F26:F27) -> #DIV/0! | G50: =SUM(G19:G22)/SUM(G26:G27) -> #DIV/0! | H50: =SUM(H19:H22)/SUM(H26:H27) -> #DIV/0! | I50: =SUM(I19:I22)/SUM(I26:I27) -> #DIV/0! | J50: =SUM(J19:J22)/SUM(J26:J27) -> #DIV/0!
C51: Quick Ratio | D51: =SUM(D19:D21)/SUM(D26:D27) -> #DIV/0! | E51: =SUM(E19:E21)/SUM(E26:E27) -> #DIV/0! | F51: =SUM(F19:F21)/SUM(F26:F27) -> #DIV/0! | G51: =SUM(G19:G21)/SUM(G26:G27) -> #DIV/0! | H51: =SUM(H19:H21)/SUM(H26:H27) -> #DIV/0! | I51: =SUM(I19:I21)/SUM(I26:I27) -> #DIV/0! | J51: =SUM(J19:J21)/SUM(J26:J27) -> #DIV/0!
B52: Efficiency | C52: Inventory Turns | D52: =ABS(D5)/D37 -> #DIV/0! | E52: =ABS(E5)/E37 -> #DIV/0! | F52: =ABS(F5)/F37 -> #DIV/0! | G52: =ABS(G5)/G37 -> #DIV/0! | H52: =ABS(H5)/H37 -> #DIV/0! | I52: =ABS(I5)/I37 -> #DIV/0! | J52: =ABS(J5)/J37 -> #DIV/0!
C53: Days in Inventory | D53: =D37/(ABS(D5)/360) -> #DIV/0! | E53: =E37/(ABS(E5)/360) -> #DIV/0! | F53: =F37/(ABS(F5)/360) -> #DIV/0! | G53: =G37/(ABS(G5)/360) -> #DIV/0! | H53: =H37/(ABS(H5)/360) -> #DIV/0! | I53: =I37/(ABS(I5)/360) -> #DIV/0! | J53: =J37/(ABS(J5)/360) -> #DIV/0!
C54: Days Payables Outstanding | D54: =D26/(ABS(D5)/360) -> #DIV/0! | E54: =E26/(ABS(E5)/360) -> #DIV/0! | F54: =F26/(ABS(F5)/360) -> #DIV/0! | G54: =G26/(ABS(G5)/360) -> #DIV/0! | H54: =H26/(ABS(H5)/360) -> #DIV/0! | I54: =I26/(ABS(I5)/360) -> #DIV/0! | J54: =J26/(ABS(J5)/360) -> #DIV/0!
C55: Days Sales Outstanding | D55: =D21/(D4/360) -> #DIV/0! | E55: =E21/(E4/360) -> #DIV/0! | F55: =F21/(F4/360) -> #DIV/0! | G55: =G21/(G4/360) -> #DIV/0! | H55: =H21/(H4/360) -> #DIV/0! | I55: =I21/(I4/360) -> #DIV/0! | J55: =J21/(J4/360) -> #DIV/0!
C56: PPE Turnover | D56: =D4/SUM(D23:D24) -> #DIV/0! | E56: =E4/SUM(E23:E24) -> #DIV/0! | F56: =F4/SUM(F23:F24) -> #DIV/0! | G56: =G4/SUM(G23:G24) -> #DIV/0! | H56: =H4/SUM(H23:H24) -> #DIV/0! | I56: =I4/SUM(I23:I24) -> #DIV/0! | J56: =J4/SUM(J23:J24) -> #DIV/0!
C57: Total Asset Turnover | D57: =D4/D25 -> #DIV/0! | E57: =E4/E25 -> #DIV/0! | F57: =F4/F25 -> #DIV/0! | G57: =G4/G25 -> #DIV/0! | H57: =H4/H25 -> #DIV/0! | I57: =I4/I25 -> #DIV/0! | J57: =J4/J25 -> #DIV/0!
C58: Cash Conversion Cycle | D58: =D53+D55-D54 -> #DIV/0! | E58: =E53+E55-E54 -> #DIV/0! | F58: =F53+F55-F54 -> #DIV/0! | G58: =G53+G55-G54 -> #DIV/0! | H58: =H53+H55-H54 -> #DIV/0! | I58: =I53+I55-I54 -> #DIV/0! | J58: =J53+J55-J54 -> #DIV/0!
B59: Other | C59: Free Cash Flow (M) | D59: =SUM(D39:D40) -> 0 | E59: =SUM(E39:E40) -> 0 | F59: =SUM(F39:F40) -> 0 | G59: =SUM(G39:G40) -> 0 | H59: =SUM(H39:H40) -> 0 | I59: =SUM(I39:I40) -> 0 | J59: =SUM(J39:J40) -> 0

Sheet Year 2
B3: Income Statement | C3: MILLIONS | D3: FIRM A | E3: FIRM B | F3: FIRM C | G3: FIRM D | H3: FIRM E | I3: FIRM F | J3: FIRM G
C4: Sales
C5: Cost of Goods Sold
C6: Gross Margin
C7: Marketing
C8: Research and Development
C9: General and Administrative
C10: Income from Operations
C11: Interest Income
C12: Interest Expense
C13: Extraordinary Items
C14: Income before Tax
C15: Less Tax @ 35%
... C17: Dividends Paid
B18: Balance Sheet | C18: MILLIONS | D18: FIRM A | E18: FIRM B | F18: FIRM C | G18: FIRM D | H18: FIRM E | I18: FIRM F | J18: FIRM G
B19: Assets | C19: Cash
C20: Short-term securities
C21: Receivables
C22: Inventory
C23: Plant and Equipment
C24: Accumulated Depreciation
C25: Total Assets
B26: Liabilities | C26: Accounts Payable
C27: Short Term Debt
C28: Long Term Debt
C29: Total Liabilities
B30: Equity | C30: Stock ($1 par)
C31: Add'l Paid in Cap.
C32: Retained Earnings
C33: Treasury Stock
C34: Total Equity
B35: Inventory Detail | C35: Beg. Inventory
C36: End. Inventory
C37: Avg. Inventory | D37: =SUM(D35:D36)/2 -> 0 | E37: =SUM(E35:E36)/2 -> 0 | F37: =SUM(F35:F36)/2 -> 0 | G37: =SUM(G35:G36)/2 -> 0 | H37: =SUM(H35:H36)/2 -> 0 | I37: =SUM(I35:I36)/2 -> 0 | J37: =SUM(J35:J36)/2 -> 0
B38: Cash Flow | C38: MILLIONS | D38: FIRM A | E38: FIRM B | F38: FIRM C | G38: FIRM D | H38: FIRM E | I38: FIRM F | J38: FIRM G
C39: Net Cash from Operations
C40: Net investment
B41: Ratios | D41: FIRM A | E41: FIRM B | F41: FIRM C | G41: FIRM D | H41: FIRM E | I41: FIRM F | J41: FIRM G
B42: Profitability | C42: Gross Profit Margin | D42: =D6/D4 -> #DIV/0! | E42: =E6/E4 -> #DIV/0! | F42: =F6/F4 -> #DIV/0! | G42: =G6/G4 -> #DIV/0! | H42: =H6/H4 -> #DIV/0! | I42: =I6/I4 -> #DIV/0! | J42: =J6/J4 -> #DIV/0!
C43: Operating Profit Margin | D43: =D10/D4 -> #DIV/0! | E43: =E10/E4 -> #DIV/0! | F43: =F10/F4 -> #DIV/0! | G43: =G10/G4 -> #DIV/0! | H43: =H10/H4 -> #DIV/0! | I43: =I10/I4 -> #DIV/0! | J43: =J10/J4 -> #DIV/0!
C44: Net Profit Margin | D44: =D16/D4 -> #DIV/0! | E44: =E16/E4 -> #DIV/0! | F44: =F16/F4 -> #DIV/0! | G44: =G16/G4 -> #DIV/0! | H44: =H16/H4 -> #DIV/0! | I44: =I16/I4 -> #DIV/0! | J44: =J16/J4 -> #DIV/0!
C45: Return on Assets | D45: =D16/D25 -> #DIV/0! | E45: =E16/E25 -> #DIV/0! | F45: =F16/F25 -> #DIV/0! | G45: =G16/G25 -> #DIV/0! | H45: =H16/H25 -> #DIV/0! | I45: =I16/I25 -> #DIV/0! | J45: =J16/J25 -> #DIV/0!
C46: Return on Equity | D46: =IF(D34<0,"N/A",D16/D34) -> #DIV/0! | E46: =IF(E34<0,"N/A",E16/E34) -> #DIV/0! | F46: =IF(F34<0,"N/A",F16/F34) -> #DIV/0! | G46: =IF(G34<0,"N/A",G16/G34) -> #DIV/0! | H46: =IF(H34<0,"N/A",H16/H34) -> #DIV/0! | I46: =IF(I34<0,"N/A",I16/I34) -> #DIV/0! | J46: =IF(J34<0,"N/A",J16/J34) -> #DIV/0!
B47: Leverage | C47: Debt-to-Equity | D47: =D29/D34 -> #DIV/0! | E47: =E29/E34 -> #DIV/0! | F47: =F29/F34 -> #DIV/0! | G47: =G29/G34 -> #DIV/0! | H47: =H29/H34 -> #DIV/0! | I47: =I29/I34 -> #DIV/0! | J47: =J29/J34 -> #DIV/0!
C48: Equity Multiplier | D48: =D25/D34 -> #DIV/0! | E48: =E25/E34 -> #DIV/0! | F48: =F25/F34 -> #DIV/0! | G48: =G25/G34 -> #DIV/0! | H48: =H25/H34 -> #DIV/0! | I48: =I25/I34 -> #DIV/0! | J48: =J25/J34 -> #DIV/0!
C49: Interest Coverage | D49: =D10/ABS(D12) -> #DIV/0! | E49: =E10/ABS(E12) -> #DIV/0! | F49: =F10/ABS(F12) -> #DIV/0! | G49: =G10/ABS(G12) -> #DIV/0! | H49: =H10/ABS(H12) -> #DIV/0! | I49: =I10/ABS(I12) -> #DIV/0! | J49: =J10/ABS(J12) -> #DIV/0!
B50: Liquidity | C50: Current Ratio | D50: =SUM(D19:D22)/SUM(D26:D27) -> #DIV/0! | E50: =SUM(E19:E22)/SUM(E26:E27) -> #DIV/0! | F50: =SUM(F19:F22)/SUM(F26:F27) -> #DIV/0! | G50: =SUM(G19:G22)/SUM(G26:G27) -> #DIV/0! | H50: =SUM(H19:H22)/SUM(H26:H27) -> #DIV/0! | I50: =SUM(I19:I22)/SUM(I26:I27) -> #DIV/0! | J50: =SUM(J19:J22)/SUM(J26:J27) -> #DIV/0!
C51: Quick Ratio | D51: =SUM(D19:D21)/SUM(D26:D27) -> #DIV/0! | E51: =SUM(E19:E21)/SUM(E26:E27) -> #DIV/0! | F51: =SUM(F19:F21)/SUM(F26:F27) -> #DIV/0! | G51: =SUM(G19:G21)/SUM(G26:G27) -> #DIV/0! | H51: =SUM(H19:H21)/SUM(H26:H27) -> #DIV/0! | I51: =SUM(I19:I21)/SUM(I26:I27) -> #DIV/0! | J51: =SUM(J19:J21)/SUM(J26:J27) -> #DIV/0!
B52: Efficiency | C52: Inventory Turns | D52: =ABS(D5)/D37 -> #DIV/0! | E52: =ABS(E5)/E37 -> #DIV/0! | F52: =ABS(F5)/F37 -> #DIV/0! | G52: =ABS(G5)/G37 -> #DIV/0! | H52: =ABS(H5)/H37 -> #DIV/0! | I52: =ABS(I5)/I37 -> #DIV/0! | J52: =ABS(J5)/J37 -> #DIV/0!
C53: Days in Inventory | D53: =D37/(ABS(D5)/360) -> #DIV/0! | E53: =E37/(ABS(E5)/360) -> #DIV/0! | F53: =F37/(ABS(F5)/360) -> #DIV/0! | G53: =G37/(ABS(G5)/360) -> #DIV/0! | H53: =H37/(ABS(H5)/360) -> #DIV/0! | I53: =I37/(ABS(I5)/360) -> #DIV/0! | J53: =J37/(ABS(J5)/360) -> #DIV/0!
C54: Days Payables Outstanding | D54: =D26/(ABS(D5)/360) -> #DIV/0! | E54: =E26/(ABS(E5)/360) -> #DIV/0! | F54: =F26/(ABS(F5)/360) -> #DIV/0! | G54: =G26/(ABS(G5)/360) -> #DIV/0! | H54: =H26/(ABS(H5)/360) -> #DIV/0! | I54: =I26/(ABS(I5)/360) -> #DIV/0! | J54: =J26/(ABS(J5)/360) -> #DIV/0!
C55: Days Sales Outstanding | D55: =D21/(D4/360) -> #DIV/0! | E55: =E21/(E4/360) -> #DIV/0! | F55: =F21/(F4/360) -> #DIV/0! | G55: =G21/(G4/360) -> #DIV/0! | H55: =H21/(H4/360) -> #DIV/0! | I55: =I21/(I4/360) -> #DIV/0! | J55: =J21/(J4/360) -> #DIV/0!
C56: PPE Turnover | D56: =D4/SUM(D23:D24) -> #DIV/0! | E56: =E4/SUM(E23:E24) -> #DIV/0! | F56: =F4/SUM(F23:F24) -> #DIV/0! | G56: =G4/SUM(G23:G24) -> #DIV/0! | H56: =H4/SUM(H23:H24) -> #DIV/0! | I56: =I4/SUM(I23:I24) -> #DIV/0! | J56: =J4/SUM(J23:J24) -> #DIV/0!
C57: Total Asset Turnover | D57: =D4/D25 -> #DIV/0! | E57: =E4/E25 -> #DIV/0! | F57: =F4/F25 -> #DIV/0! | G57: =G4/G25 -> #DIV/0! | H57: =H4/H25 -> #DIV/0! | I57: =I4/I25 -> #DIV/0! | J57: =J4/J25 -> #DIV/0!
C58: Cash Conversion Cycle | D58: =D53+D55-D54 -> #DIV/0! | E58: =E53+E55-E54 -> #DIV/0! | F58: =F53+F55-F54 -> #DIV/0! | G58: =G53+G55-G54 -> #DIV/0! | H58: =H53+H55-H54 -> #DIV/0! | I58: =I53+I55-I54 -> #DIV/0! | J58: =J53+J55-J54 -> #DIV/0!
B59: Other | C59: Free Cash Flow (M) | D59: =SUM(D39:D40) -> 0 | E59: =SUM(E39:E40) -> 0 | F59: =SUM(F39:F40) -> 0 | G59: =SUM(G39:G40) -> 0 | H59: =SUM(H39:H40) -> 0 | I59: =SUM(I39:I40) -> 0 | J59: =SUM(J39:J40) -> 0

Sheet Year 3
B3: Income Statement | C3: MILLIONS | D3: FIRM A | E3: FIRM B | F3: FIRM C | G3: FIRM D | H3: FIRM E | I3: FIRM F | J3: FIRM G
C4: Sales
C5: Cost of Goods Sold
C6: Gross Margin
C7: Marketing
C8: Research and Development
C9: General and Administrative
C10: Income from Operations
C11: Interest Income
C12: Interest Expense
C13: Extraordinary Items
C14: Income before Tax
C15: Less Tax @ 35%
... C17: Dividends Paid
B18: Balance Sheet | C18: MILLIONS | D18: FIRM A | E18: FIRM B | F18: FIRM C | G18: FIRM D | H18: FIRM E | I18: FIRM F | J18: FIRM G
B19: Assets | C19: Cash
C20: Short-term securities
C21: Receivables
C22: Inventory
C23: Plant and Equipment
C24: Accumulated Depreciation
C25: Total Assets
B26: Liabilities | C26: Accounts Payable
C27: Short Term Debt
C28: Long Term Debt
C29: Total Liabilities
B30: Equity | C30: Stock ($1 par)
C31: Add'l Paid in Cap.
C32: Retained Earnings
C33: Treasury Stock
C34: Total Equity
B35: Inventory Detail | C35: Beg. Inventory
C36: End. Inventory
C37: Avg. Inventory | D37: =SUM(D35:D36)/2 -> 0 | E37: =SUM(E35:E36)/2 -> 0 | F37: =SUM(F35:F36)/2 -> 0 | G37: =SUM(G35:G36)/2 -> 0 | H37: =SUM(H35:H36)/2 -> 0 | I37: =SUM(I35:I36)/2 -> 0 | J37: =SUM(J35:J36)/2 -> 0
B38: Cash Flow | C38: MILLIONS | D38: FIRM A | E38: FIRM B | F38: FIRM C | G38: FIRM D | H38: FIRM E | I38: FIRM F | J38: FIRM G
C39: Net Cash from Operations
C40: Net investment
B41: Ratios | D41: FIRM A | E41: FIRM B | F41: FIRM C | G41: FIRM D | H41: FIRM E | I41: FIRM F | J41: FIRM G
B42: Profitability | C42: Gross Profit Margin | D42: =D6/D4 -> #DIV/0! | E42: =E6/E4 -> #DIV/0! | F42: =F6/F4 -> #DIV/0! | G42: =G6/G4 -> #DIV/0! | H42: =H6/H4 -> #DIV/0! | I42: =I6/I4 -> #DIV/0! | J42: =J6/J4 -> #DIV/0!
C43: Operating Profit Margin | D43: =D10/D4 -> #DIV/0! | E43: =E10/E4 -> #DIV/0! | F43: =F10/F4 -> #DIV/0! | G43: =G10/G4 -> #DIV/0! | H43: =H10/H4 -> #DIV/0! | I43: =I10/I4 -> #DIV/0! | J43: =J10/J4 -> #DIV/0!
C44: Net Profit Margin | D44: =D16/D4 -> #DIV/0! | E44: =E16/E4 -> #DIV/0! | F44: =F16/F4 -> #DIV/0! | G44: =G16/G4 -> #DIV/0! | H44: =H16/H4 -> #DIV/0! | I44: =I16/I4 -> #DIV/0! | J44: =J16/J4 -> #DIV/0!
C45: Return on Assets | D45: =D16/D25 -> #DIV/0! | E45: =E16/E25 -> #DIV/0! | F45: =F16/F25 -> #DIV/0! | G45: =G16/G25 -> #DIV/0! | H45: =H16/H25 -> #DIV/0! | I45: =I16/I25 -> #DIV/0! | J45: =J16/J25 -> #DIV/0!
C46: Return on Equity | D46: =IF(D34<0,"N/A",D16/D34) -> #DIV/0! | E46: =IF(E34<0,"N/A",E16/E34) -> #DIV/0! | F46: =IF(F34<0,"N/A",F16/F34) -> #DIV/0! | G46: =IF(G34<0,"N/A",G16/G34) -> #DIV/0! | H46: =IF(H34<0,"N/A",H16/H34) -> #DIV/0! | I46: =IF(I34<0,"N/A",I16/I34) -> #DIV/0! | J46: =IF(J34<0,"N/A",J16/J34) -> #DIV/0!
B47: Leverage | C47: Debt-to-Equity | D47: =D29/D34 -> #DIV/0! | E47: =E29/E34 -> #DIV/0! | F47: =F29/F34 -> #DIV/0! | G47: =G29/G34 -> #DIV/0! | H47: =H29/H34 -> #DIV/0! | I47: =I29/I34 -> #DIV/0! | J47: =J29/J34 -> #DIV/0!
C48: Equity Multiplier | D48: =D25/D34 -> #DIV/0! | E48: =E25/E34 -> #DIV/0! | F48: =F25/F34 -> #DIV/0! | G48: =G25/G34 -> #DIV/0! | H48: =H25/H34 -> #DIV/0! | I48: =I25/I34 -> #DIV/0! | J48: =J25/J34 -> #DIV/0!
C49: Interest Coverage | D49: =D10/ABS(D12) -> #DIV/0! | E49: =E10/ABS(E12) -> #DIV/0! | F49: =F10/ABS(F12) -> #DIV/0! | G49: =G10/ABS(G12) -> #DIV/0! | H49: =H10/ABS(H12) -> #DIV/0! | I49: =I10/ABS(I12) -> #DIV/0! | J49: =J10/ABS(J12) -> #DIV/0!
B50: Liquidity | C50: Current Ratio | D50: =SUM(D19:D22)/SUM(D26:D27) -> #DIV/0! | E50: =SUM(E19:E22)/SUM(E26:E27) -> #DIV/0! | F50: =SUM(F19:F22)/SUM(F26:F27) -> #DIV/0! | G50: =SUM(G19:G22)/SUM(G26:G27) -> #DIV/0! | H50: =SUM(H19:H22)/SUM(H26:H27) -> #DIV/0! | I50: =SUM(I19:I22)/SUM(I26:I27) -> #DIV/0! | J50: =SUM(J19:J22)/SUM(J26:J27) -> #DIV/0!
C51: Quick Ratio | D51: =SUM(D19:D21)/SUM(D26:D27) -> #DIV/0! | E51: =SUM(E19:E21)/SUM(E26:E27) -> #DIV/0! | F51: =SUM(F19:F21)/SUM(F26:F27) -> #DIV/0! | G51: =SUM(G19:G21)/SUM(G26:G27) -> #DIV/0! | H51: =SUM(H19:H21)/SUM(H26:H27) -> #DIV/0! | I51: =SUM(I19:I21)/SUM(I26:I27) -> #DIV/0! | J51: =SUM(J19:J21)/SUM(J26:J27) -> #DIV/0!
B52: Efficiency | C52: Inventory Turns | D52: =ABS(D5)/D37 -> #DIV/0! | E52: =ABS(E5)/E37 -> #DIV/0! | F52: =ABS(F5)/F37 -> #DIV/0! | G52: =ABS(G5)/G37 -> #DIV/0! | H52: =ABS(H5)/H37 -> #DIV/0! | I52: =ABS(I5)/I37 -> #DIV/0! | J52: =ABS(J5)/J37 -> #DIV/0!
C53: Days in Inventory | D53: =D37/(ABS(D5)/360) -> #DIV/0! | E53: =E37/(ABS(E5)/360) -> #DIV/0! | F53: =F37/(ABS(F5)/360) -> #DIV/0! | G53: =G37/(ABS(G5)/360) -> #DIV/0! | H53: =H37/(ABS(H5)/360) -> #DIV/0! | I53: =I37/(ABS(I5)/360) -> #DIV/0! | J53: =J37/(ABS(J5)/360) -> #DIV/0!
C54: Days Payables Outstanding | D54: =D26/(ABS(D5)/360) -> #DIV/0! | E54: =E26/(ABS(E5)/360) -> #DIV/0! | F54: =F26/(ABS(F5)/360) -> #DIV/0! | G54: =G26/(ABS(G5)/360) -> #DIV/0! | H54: =H26/(ABS(H5)/360) -> #DIV/0! | I54: =I26/(ABS(I5)/360) -> #DIV/0! | J54: =J26/(ABS(J5)/360) -> #DIV/0!
C55: Days Sales Outstanding | D55: =D21/(D4/360) -> #DIV/0! | E55: =E21/(E4/360) -> #DIV/0! | F55: =F21/(F4/360) -> #DIV/0! | G55: =G21/(G4/360) -> #DIV/0! | H55: =H21/(H4/360) -> #DIV/0! | I55: =I21/(I4/360) -> #DIV/0! | J55: =J21/(J4/360) -> #DIV/0!
C56: PPE Turnover | D56: =D4/SUM(D23:D24) -> #DIV/0! | E56: =E4/SUM(E23:E24) -> #DIV/0! | F56: =F4/SUM(F23:F24) -> #DIV/0! | G56: =G4/SUM(G23:G24) -> #DIV/0! | H56: =H4/SUM(H23:H24) -> #DIV/0! | I56: =I4/SUM(I23:I24) -> #DIV/0! | J56: =J4/SUM(J23:J24) -> #DIV/0!
C57: Total Asset Turnover | D57: =D4/D25 -> #DIV/0! | E57: =E4/E25 -> #DIV/0! | F57: =F4/F25 -> #DIV/0! | G57: =G4/G25 -> #DIV/0! | H57: =H4/H25 -> #DIV/0! | I57: =I4/I25 -> #DIV/0! | J57: =J4/J25 -> #DIV/0!
C58: Cash Conversion Cycle | D58: =D53+D55-D54 -> #DIV/0! | E58: =E53+E55-E54 -> #DIV/0! | F58: =F53+F55-F54 -> #DIV/0! | G58: =G53+G55-G54 -> #DIV/0! | H58: =H53+H55-H54 -> #DIV/0! | I58: =I53+I55-I54 -> #DIV/0! | J58: =J53+J55-J54 -> #DIV/0!
B59: Other | C59: Free Cash Flow (M) | D59: =SUM(D39:D40) -> 0 | E59: =SUM(E39:E40) -> 0 | F59: =SUM(F39:F40) -> 0 | G59: =SUM(G39:G40) -> 0 | H59: =SUM(H39:H40) -> 0 | I59: =SUM(I39:I40) -> 0 | J59: =SUM(J39:J40) -> 0

Sheet Year 4
B3: Income Statement | C3: MILLIONS | D3: FIRM A | E3: FIRM B | F3: FIRM C | G3: FIRM D | H3: FIRM E | I3: FIRM F | J3: FIRM G
C4: Sales
C5: Cost of Goods Sold
C6: Gross Margin
C7: Marketing
C8: Research and Development
C9: General and Administrative
C10: Income from Operations
C11: Interest Income
C12: Interest Expense
C13: Extraordinary Items
C14: Income before Tax
C15: Less Tax @ 35%
... C17: Dividends Paid
B18: Balance Sheet | C18: MILLIONS | D18: FIRM A | E18: FIRM B | F18: FIRM C | G18: FIRM D | H18: FIRM E | I18: FIRM F | J18: FIRM G
B19: Assets | C19: Cash
C20: Short-term securities
C21: Receivables
C22: Inventory
C23: Plant and Equipment
C24: Accumulated Depreciation
C25: Total Assets
B26: Liabilities | C26: Accounts Payable
C27: Short Term Debt
C28: Long Term Debt
C29: Total Liabilities
B30: Equity | C30: Stock ($1 par)
C31: Add'l Paid in Cap.
C32: Retained Earnings
C33: Treasury Stock
C34: Total Equity
B35: Inventory Detail | C35: Beg. Inventory
C36: End. Inventory
C37: Avg. Inventory | D37: =SUM(D35:D36)/2 -> 0 | E37: =SUM(E35:E36)/2 -> 0 | F37: =SUM(F35:F36)/2 -> 0 | G37: =SUM(G35:G36)/2 -> 0 | H37: =SUM(H35:H36)/2 -> 0 | I37: =SUM(I35:I36)/2 -> 0 | J37: =SUM(J35:J36)/2 -> 0
B38: Cash Flow | C38: MILLIONS | D38: FIRM A | E38: FIRM B | F38: FIRM C | G38: FIRM D | H38: FIRM E | I38: FIRM F | J38: FIRM G
C39: Net Cash from Operations
C40: Net investment
B41: Ratios | D41: FIRM A | E41: FIRM B | F41: FIRM C | G41: FIRM D | H41: FIRM E | I41: FIRM F | J41: FIRM G
B42: Profitability | C42: Gross Profit Margin | D42: =D6/D4 -> #DIV/0! | E42: =E6/E4 -> #DIV/0! | F42: =F6/F4 -> #DIV/0! | G42: =G6/G4 -> #DIV/0! | H42: =H6/H4 -> #DIV/0! | I42: =I6/I4 -> #DIV/0! | J42: =J6/J4 -> #DIV/0!
C43: Operating Profit Margin | D43: =D10/D4 -> #DIV/0! | E43: =E10/E4 -> #DIV/0! | F43: =F10/F4 -> #DIV/0! | G43: =G10/G4 -> #DIV/0! | H43: =H10/H4 -> #DIV/0! | I43: =I10/I4 -> #DIV/0! | J43: =J10/J4 -> #DIV/0!
C44: Net Profit Margin | D44: =D16/D4 -> #DIV/0! | E44: =E16/E4 -> #DIV/0! | F44: =F16/F4 -> #DIV/0! | G44: =G16/G4 -> #DIV/0! | H44: =H16/H4 -> #DIV/0! | I44: =I16/I4 -> #DIV/0! | J44: =J16/J4 -> #DIV/0!
C45: Return on Assets | D45: =D16/D25 -> #DIV/0! | E45: =E16/E25 -> #DIV/0! | F45: =F16/F25 -> #DIV/0! | G45: =G16/G25 -> #DIV/0! | H45: =H16/H25 -> #DIV/0! | I45: =I16/I25 -> #DIV/0! | J45: =J16/J25 -> #DIV/0!
C46: Return on Equity | D46: =IF(D34<0,"N/A",D16/D34) -> #DIV/0! | E46: =IF(E34<0,"N/A",E16/E34) -> #DIV/0! | F46: =IF(F34<0,"N/A",F16/F34) -> #DIV/0! | G46: =IF(G34<0,"N/A",G16/G34) -> #DIV/0! | H46: =IF(H34<0,"N/A",H16/H34) -> #DIV/0! | I46: =IF(I34<0,"N/A",I16/I34) -> #DIV/0! | J46: =IF(J34<0,"N/A",J16/J34) -> #DIV/0!
B47: Leverage | C47: Debt-to-Equity | D47: =D29/D34 -> #DIV/0! | E47: =E29/E34 -> #DIV/0! | F47: =F29/F34 -> #DIV/0! | G47: =G29/G34 -> #DIV/0! | H47: =H29/H34 -> #DIV/0! | I47: =I29/I34 -> #DIV/0! | J47: =J29/J34 -> #DIV/0!
C48: Equity Multiplier | D48: =D25/D34 -> #DIV/0! | E48: =E25/E34 -> #DIV/0! | F48: =F25/F34 -> #DIV/0! | G48: =G25/G34 -> #DIV/0! | H48: =H25/H34 -> #DIV/0! | I48: =I25/I34 -> #DIV/0! | J48: =J25/J34 -> #DIV/0!
C49: Interest Coverage | D49: =D10/ABS(D12) -> #DIV/0! | E49: =E10/ABS(E12) -> #DIV/0! | F49: =F10/ABS(F12) -> #DIV/0! | G49: =G10/ABS(G12) -> #DIV/0! | H49: =H10/ABS(H12) -> #DIV/0! | I49: =I10/ABS(I12) -> #DIV/0! | J49: =J10/ABS(J12) -> #DIV/0!
B50: Liquidity | C50: Current Ratio | D50: =SUM(D19:D22)/SUM(D26:D27) -> #DIV/0! | E50: =SUM(E19:E22)/SUM(E26:E27) -> #DIV/0! | F50: =SUM(F19:F22)/SUM(F26:F27) -> #DIV/0! | G50: =SUM(G19:G22)/SUM(G26:G27) -> #DIV/0! | H50: =SUM(H19:H22)/SUM(H26:H27) -> #DIV/0! | I50: =SUM(I19:I22)/SUM(I26:I27) -> #DIV/0! | J50: =SUM(J19:J22)/SUM(J26:J27) -> #DIV/0!
C51: Quick Ratio | D51: =SUM(D19:D21)/SUM(D26:D27) -> #DIV/0! | E51: =SUM(E19:E21)/SUM(E26:E27) -> #DIV/0! | F51: =SUM(F19:F21)/SUM(F26:F27) -> #DIV/0! | G51: =SUM(G19:G21)/SUM(G26:G27) -> #DIV/0! | H51: =SUM(H19:H21)/SUM(H26:H27) -> #DIV/0! | I51: =SUM(I19:I21)/SUM(I26:I27) -> #DIV/0! | J51: =SUM(J19:J21)/SUM(J26:J27) -> #DIV/0!
B52: Efficiency | C52: Inventory Turns | D52: =ABS(D5)/D37 -> #DIV/0! | E52: =ABS(E5)/E37 -> #DIV/0! | F52: =ABS(F5)/F37 -> #DIV/0! | G52: =ABS(G5)/G37 -> #DIV/0! | H52: =ABS(H5)/H37 -> #DIV/0! | I52: =ABS(I5)/I37 -> #DIV/0! | J52: =ABS(J5)/J37 -> #DIV/0!
C53: Days in Inventory | D53: =D37/(ABS(D5)/360) -> #DIV/0! | E53: =E37/(ABS(E5)/360) -> #DIV/0! | F53: =F37/(ABS(F5)/360) -> #DIV/0! | G53: =G37/(ABS(G5)/360) -> #DIV/0! | H53: =H37/(ABS(H5)/360) -> #DIV/0! | I53: =I37/(ABS(I5)/360) -> #DIV/0! | J53: =J37/(ABS(J5)/360) -> #DIV/0!
C54: Days Payables Outstanding | D54: =D26/(ABS(D5)/360) -> #DIV/0! | E54: =E26/(ABS(E5)/360) -> #DIV/0! | F54: =F26/(ABS(F5)/360) -> #DIV/0! | G54: =G26/(ABS(G5)/360) -> #DIV/0! | H54: =H26/(ABS(H5)/360) -> #DIV/0! | I54: =I26/(ABS(I5)/360) -> #DIV/0! | J54: =J26/(ABS(J5)/360) -> #DIV/0!
C55: Days Sales Outstanding | D55: =D21/(D4/360) -> #DIV/0! | E55: =E21/(E4/360) -> #DIV/0! | F55: =F21/(F4/360) -> #DIV/0! | G55: =G21/(G4/360) -> #DIV/0! | H55: =H21/(H4/360) -> #DIV/0! | I55: =I21/(I4/360) -> #DIV/0! | J55: =J21/(J4/360) -> #DIV/0!
C56: PPE Turnover | D56: =D4/SUM(D23:D24) -> #DIV/0! | E56: =E4/SUM(E23:E24) -> #DIV/0! | F56: =F4/SUM(F23:F24) -> #DIV/0! | G56: =G4/SUM(G23:G24) -> #DIV/0! | H56: =H4/SUM(H23:H24) -> #DIV/0! | I56: =I4/SUM(I23:I24) -> #DIV/0! | J56: =J4/SUM(J23:J24) -> #DIV/0!
C57: Total Asset Turnover | D57: =D4/D25 -> #DIV/0! | E57: =E4/E25 -> #DIV/0! | F57: =F4/F25 -> #DIV/0! | G57: =G4/G25 -> #DIV/0! | H57: =H4/H25 -> #DIV/0! | I57: =I4/I25 -> #DIV/0! | J57: =J4/J25 -> #DIV/0!
C58: Cash Conversion Cycle | D58: =D53+D55-D54 -> #DIV/0! | E58: =E53+E55-E54 -> #DIV/0! | F58: =F53+F55-F54 -> #DIV/0! | G58: =G53+G55-G54 -> #DIV/0! | H58: =H53+H55-H54 -> #DIV/0! | I58: =I53+I55-I54 -> #DIV/0! | J58: =J53+J55-J54 -> #DIV/0!
B59: Other | C59: Free Cash Flow (M) | D59: =SUM(D39:D40) -> 0 | E59: =SUM(E39:E40) -> 0 | F59: =SUM(F39:F40) -> 0 | G59: =SUM(G39:G40) -> 0 | H59: =SUM(H39:H40) -> 0 | I59: =SUM(I39:I40) -> 0 | J59: =SUM(J39:J40) -> 0

Sheet Year 5
B3: Income Statement | C3: MILLIONS | D3: FIRM A | E3: FIRM B | F3: FIRM C | G3: FIRM D | H3: FIRM E | I3: FIRM F | J3: FIRM G
C4: Sales
C5: Cost of Goods Sold
C6: Gross Margin
C7: Marketing
C8: Research and Development
C9: General and Administrative
C10: Income from Operations
C11: Interest Income
C12: Interest Expense
C13: Extraordinary Items
C14: Income before Tax
C15: Less Tax @ 35%
... C17: Dividends Paid
B18: Balance Sheet | C18: MILLIONS | D18: FIRM A | E18: FIRM B | F18: FIRM C | G18: FIRM D | H18: FIRM E | I18: FIRM F | J18: FIRM G
B19: Assets | C19: Cash
C20: Short-term securities
C21: Receivables
C22: Inventory
C23: Plant and Equipment
C24: Accumulated Depreciation
C25: Total Assets
B26: Liabilities | C26: Accounts Payable
C27: Short Term Debt
C28: Long Term Debt
C29: Total Liabilities
B30: Equity | C30: Stock ($1 par)
C31: Add'l Paid in Cap.
C32: Retained Earnings
C33: Treasury Stock
C34: Total Equity
B35: Inventory Detail | C35: Beg. Inventory
C36: End. Inventory
C37: Avg. Inventory | D37: =SUM(D35:D36)/2 -> 0 | E37: =SUM(E35:E36)/2 -> 0 | F37: =SUM(F35:F36)/2 -> 0 | G37: =SUM(G35:G36)/2 -> 0 | H37: =SUM(H35:H36)/2 -> 0 | I37: =SUM(I35:I36)/2 -> 0 | J37: =SUM(J35:J36)/2 -> 0
B38: Cash Flow | C38: MILLIONS | D38: FIRM A | E38: FIRM B | F38: FIRM C | G38: FIRM D | H38: FIRM E | I38: FIRM F | J38: FIRM G
C39: Net Cash from Operations
C40: Net investment
B41: Ratios | D41: FIRM A | E41: FIRM B | F41: FIRM C | G41: FIRM D | H41: FIRM E | I41: FIRM F | J41: FIRM G
B42: Profitability | C42: Gross Profit Margin | D42: =D6/D4 -> #DIV/0! | E42: =E6/E4 -> #DIV/0! | F42: =F6/F4 -> #DIV/0! | G42: =G6/G4 -> #DIV/0! | H42: =H6/H4 -> #DIV/0! | I42: =I6/I4 -> #DIV/0! | J42: =J6/J4 -> #DIV/0!
C43: Operating Profit Margin | D43: =D10/D4 -> #DIV/0! | E43: =E10/E4 -> #DIV/0! | F43: =F10/F4 -> #DIV/0! | G43: =G10/G4 -> #DIV/0! | H43: =H10/H4 -> #DIV/0! | I43: =I10/I4 -> #DIV/0! | J43: =J10/J4 -> #DIV/0!
C44: Net Profit Margin | D44: =D16/D4 -> #DIV/0! | E44: =E16/E4 -> #DIV/0! | F44: =F16/F4 -> #DIV/0! | G44: =G16/G4 -> #DIV/0! | H44: =H16/H4 -> #DIV/0! | I44: =I16/I4 -> #DIV/0! | J44: =J16/J4 -> #DIV/0!
C45: Return on Assets | D45: =D16/D25 -> #DIV/0! | E45: =E16/E25 -> #DIV/0! | F45: =F16/F25 -> #DIV/0! | G45: =G16/G25 -> #DIV/0! | H45: =H16/H25 -> #DIV/0! | I45: =I16/I25 -> #DIV/0! | J45: =J16/J25 -> #DIV/0!
C46: Return on Equity | D46: =IF(D34<0,"N/A",D16/D34) -> #DIV/0! | E46: =IF(E34<0,"N/A",E16/E34) -> #DIV/0! | F46: =IF(F34<0,"N/A",F16/F34) -> #DIV/0! | G46: =IF(G34<0,"N/A",G16/G34) -> #DIV/0! | H46: =IF(H34<0,"N/A",H16/H34) -> #DIV/0! | I46: =IF(I34<0,"N/A",I16/I34) -> #DIV/0! | J46: =IF(J34<0,"N/A",J16/J34) -> #DIV/0!
B47: Leverage | C47: Debt-to-Equity | D47: =D29/D34 -> #DIV/0! | E47: =E29/E34 -> #DIV/0! | F47: =F29/F34 -> #DIV/0! | G47: =G29/G34 -> #DIV/0! | H47: =H29/H34 -> #DIV/0! | I47: =I29/I34 -> #DIV/0! | J47: =J29/J34 -> #DIV/0!
C48: Equity Multiplier | D48: =D25/D34 -> #DIV/0! | E48: =E25/E34 -> #DIV/0! | F48: =F25/F34 -> #DIV/0! | G48: =G25/G34 -> #DIV/0! | H48: =H25/H34 -> #DIV/0! | I48: =I25/I34 -> #DIV/0! | J48: =J25/J34 -> #DIV/0!
C49: Interest Coverage | D49: =D10/ABS(D12) -> #DIV/0! | E49: =E10/ABS(E12) -> #DIV/0! | F49: =F10/ABS(F12) -> #DIV/0! | G49: =G10/ABS(G12) -> #DIV/0! | H49: =H10/ABS(H12) -> #DIV/0! | I49: =I10/ABS(I12) -> #DIV/0! | J49: =J10/ABS(J12) -> #DIV/0!
B50: Liquidity | C50: Current Ratio | D50: =SUM(D19:D22)/SUM(D26:D27) -> #DIV/0! | E50: =SUM(E19:E22)/SUM(E26:E27) -> #DIV/0! | F50: =SUM(F19:F22)/SUM(F26:F27) -> #DIV/0! | G50: =SUM(G19:G22)/SUM(G26:G27) -> #DIV/0! | H50: =SUM(H19:H22)/SUM(H26:H27) -> #DIV/0! | I50: =SUM(I19:I22)/SUM(I26:I27) -> #DIV/0! | J50: =SUM(J19:J22)/SUM(J26:J27) -> #DIV/0!
C51: Quick Ratio | D51: =SUM(D19:D21)/SUM(D26:D27) -> #DIV/0! | E51: =SUM(E19:E21)/SUM(E26:E27) -> #DIV/0! | F51: =SUM(F19:F21)/SUM(F26:F27) -> #DIV/0! | G51: =SUM(G19:G21)/SUM(G26:G27) -> #DIV/0! | H51: =SUM(H19:H21)/SUM(H26:H27) -> #DIV/0! | I51: =SUM(I19:I21)/SUM(I26:I27) -> #DIV/0! | J51: =SUM(J19:J21)/SUM(J26:J27) -> #DIV/0!
B52: Efficiency | C52: Inventory Turns | D52: =ABS(D5)/D37 -> #DIV/0! | E52: =ABS(E5)/E37 -> #DIV/0! | F52: =ABS(F5)/F37 -> #DIV/0! | G52: =ABS(G5)/G37 -> #DIV/0! | H52: =ABS(H5)/H37 -> #DIV/0! | I52: =ABS(I5)/I37 -> #DIV/0! | J52: =ABS(J5)/J37 -> #DIV/0!
C53: Days in Inventory | D53: =D37/(ABS(D5)/360) -> #DIV/0! | E53: =E37/(ABS(E5)/360) -> #DIV/0! | F53: =F37/(ABS(F5)/360) -> #DIV/0! | G53: =G37/(ABS(G5)/360) -> #DIV/0! | H53: =H37/(ABS(H5)/360) -> #DIV/0! | I53: =I37/(ABS(I5)/360) -> #DIV/0! | J53: =J37/(ABS(J5)/360) -> #DIV/0!
C54: Days Payables Outstanding | D54: =D26/(ABS(D5)/360) -> #DIV/0! | E54: =E26/(ABS(E5)/360) -> #DIV/0! | F54: =F26/(ABS(F5)/360) -> #DIV/0! | G54: =G26/(ABS(G5)/360) -> #DIV/0! | H54: =H26/(ABS(H5)/360) -> #DIV/0! | I54: =I26/(ABS(I5)/360) -> #DIV/0! | J54: =J26/(ABS(J5)/360) -> #DIV/0!
C55: Days Sales Outstanding | D55: =D21/(D4/360) -> #DIV/0! | E55: =E21/(E4/360) -> #DIV/0! | F55: =F21/(F4/360) -> #DIV/0! | G55: =G21/(G4/360) -> #DIV/0! | H55: =H21/(H4/360) -> #DIV/0! | I55: =I21/(I4/360) -> #DIV/0! | J55: =J21/(J4/360) -> #DIV/0!
C56: PPE Turnover | D56: =D4/SUM(D23:D24) -> #DIV/0! | E56: =E4/SUM(E23:E24) -> #DIV/0! | F56: =F4/SUM(F23:F24) -> #DIV/0! | G56: =G4/SUM(G23:G24) -> #DIV/0! | H56: =H4/SUM(H23:H24) -> #DIV/0! | I56: =I4/SUM(I23:I24) -> #DIV/0! | J56: =J4/SUM(J23:J24) -> #DIV/0!
C57: Total Asset Turnover | D57: =D4/D25 -> #DIV/0! | E57: =E4/E25 -> #DIV/0! | F57: =F4/F25 -> #DIV/0! | G57: =G4/G25 -> #DIV/0! | H57: =H4/H25 -> #DIV/0! | I57: =I4/I25 -> #DIV/0! | J57: =J4/J25 -> #DIV/0!
C58: Cash Conversion Cycle | D58: =D53+D55-D54 -> #DIV/0! | E58: =E53+E55-E54 -> #DIV/0! | F58: =F53+F55-F54 -> #DIV/0! | G58: =G53+G55-G54 -> #DIV/0! | H58: =H53+H55-H54 -> #DIV/0! | I58: =I53+I55-I54 -> #DIV/0! | J58: =J53+J55-J54 -> #DIV/0!
B59: Other | C59: Free Cash Flow (M) | D59: =SUM(D39:D40) -> 0 | E59: =SUM(E39:E40) -> 0 | F59: =SUM(F39:F40) -> 0 | G59: =SUM(G39:G40) -> 0 | H59: =SUM(H39:H40) -> 0 | I59: =SUM(I39:I40) -> 0 | J59: =SUM(J39:J40) -> 0

Sheet Year 6
B3: Income Statement | C3: MILLIONS | D3: FIRM A | E3: FIRM B | F3: FIRM C | G3: FIRM D | H3: FIRM E | I3: FIRM F | J3: FIRM G
C4: Sales
C5: Cost of Goods Sold
C6: Gross Margin
C7: Marketing
C8: Research and Development
C9: General and Administrative
C10: Income from Operations
C11: Interest Income
C12: Interest Expense
C13: Extraordinary Items
C14: Income before Tax
C15: Less Tax @ 35%
... C17: Dividends Paid
B18: Balance Sheet | C18: MILLIONS | D18: FIRM A | E18: FIRM B | F18: FIRM C | G18: FIRM D | H18: FIRM E | I18: FIRM F | J18: FIRM G
B19: Assets | C19: Cash
C20: Short-term securities
C21: Receivables
C22: Inventory
C23: Plant and Equipment
C24: Accumulated Depreciation
C25: Total Assets
B26: Liabilities | C26: Accounts Payable
C27: Short Term Debt
C28: Long Term Debt
C29: Total Liabilities
B30: Equity | C30: Stock ($1 par)
C31: Add'l Paid in Cap.
C32: Retained Earnings
C33: Treasury Stock
C34: Total Equity
B35: Inventory Detail | C35: Beg. Inventory
C36: End. Inventory
C37: Avg. Inventory | D37: =SUM(D35:D36)/2 -> 0 | E37: =SUM(E35:E36)/2 -> 0 | F37: =SUM(F35:F36)/2 -> 0 | G37: =SUM(G35:G36)/2 -> 0 | H37: =SUM(H35:H36)/2 -> 0 | I37: =SUM(I35:I36)/2 -> 0 | J37: =SUM(J35:J36)/2 -> 0
B38: Cash Flow | C38: MILLIONS | D38: FIRM A | E38: FIRM B | F38: FIRM C | G38: FIRM D | H38: FIRM E | I38: FIRM F | J38: FIRM G
C39: Net Cash from Operations
C40: Net investment
B41: Ratios | D41: FIRM A | E41: FIRM B | F41: FIRM C | G41: FIRM D | H41: FIRM E | I41: FIRM F | J41: FIRM G
B42: Profitability | C42: Gross Profit Margin | D42: =D6/D4 -> #DIV/0! | E42: =E6/E4 -> #DIV/0! | F42: =F6/F4 -> #DIV/0! | G42: =G6/G4 -> #DIV/0! | H42: =H6/H4 -> #DIV/0! | I42: =I6/I4 -> #DIV/0! | J42: =J6/J4 -> #DIV/0!
C43: Operating Profit Margin | D43: =D10/D4 -> #DIV/0! | E43: =E10/E4 -> #DIV/0! | F43: =F10/F4 -> #DIV/0! | G43: =G10/G4 -> #DIV/0! | H43: =H10/H4 -> #DIV/0! | I43: =I10/I4 -> #DIV/0! | J43: =J10/J4 -> #DIV/0!
C44: Net Profit Margin | D44: =D16/D4 -> #DIV/0! | E44: =E16/E4 -> #DIV/0! | F44: =F16/F4 -> #DIV/0! | G44: =G16/G4 -> #DIV/0! | H44: =H16/H4 -> #DIV/0! | I44: =I16/I4 -> #DIV/0! | J44: =J16/J4 -> #DIV/0!
C45: Return on Assets | D45: =D16/D25 -> #DIV/0! | E45: =E16/E25 -> #DIV/0! | F45: =F16/F25 -> #DIV/0! | G45: =G16/G25 -> #DIV/0! | H45: =H16/H25 -> #DIV/0! | I45: =I16/I25 -> #DIV/0! | J45: =J16/J25 -> #DIV/0!
C46: Return on Equity | D46: =IF(D34<0,"N/A",D16/D34) -> #DIV/0! | E46: =IF(E34<0,"N/A",E16/E34) -> #DIV/0! | F46: =IF(F34<0,"N/A",F16/F34) -> #DIV/0! | G46: =IF(G34<0,"N/A",G16/G34) -> #DIV/0! | H46: =IF(H34<0,"N/A",H16/H34) -> #DIV/0! | I46: =IF(I34<0,"N/A",I16/I34) -> #DIV/0! | J46: =IF(J34<0,"N/A",J16/J34) -> #DIV/0!
B47: Leverage | C47: Debt-to-Equity | D47: =D29/D34 -> #DIV/0! | E47: =E29/E34 -> #DIV/0! | F47: =F29/F34 -> #DIV/0! | G47: =G29/G34 -> #DIV/0! | H47: =H29/H34 -> #DIV/0! | I47: =I29/I34 -> #DIV/0! | J47: =J29/J34 -> #DIV/0!
C48: Equity Multiplier | D48: =D25/D34 -> #DIV/0! | E48: =E25/E34 -> #DIV/0! | F48: =F25/F34 -> #DIV/0! | G48: =G25/G34 -> #DIV/0! | H48: =H25/H34 -> #DIV/0! | I48: =I25/I34 -> #DIV/0! | J48: =J25/J34 -> #DIV/0!
C49: Interest Coverage | D49: =D10/ABS(D12) -> #DIV/0! | E49: =E10/ABS(E12) -> #DIV/0! | F49: =F10/ABS(F12) -> #DIV/0! | G49: =G10/ABS(G12) -> #DIV/0! | H49: =H10/ABS(H12) -> #DIV/0! | I49: =I10/ABS(I12) -> #DIV/0! | J49: =J10/ABS(J12) -> #DIV/0!
B50: Liquidity | C50: Current Ratio | D50: =SUM(D19:D22)/SUM(D26:D27) -> #DIV/0! | E50: =SUM(E19:E22)/SUM(E26:E27) -> #DIV/0! | F50: =SUM(F19:F22)/SUM(F26:F27) -> #DIV/0! | G50: =SUM(G19:G22)/SUM(G26:G27) -> #DIV/0! | H50: =SUM(H19:H22)/SUM(H26:H27) -> #DIV/0! | I50: =SUM(I19:I22)/SUM(I26:I27) -> #DIV/0! | J50: =SUM(J19:J22)/SUM(J26:J27) -> #DIV/0!
C51: Quick Ratio | D51: =SUM(D19:D21)/SUM(D26:D27) -> #DIV/0! | E51: =SUM(E19:E21)/SUM(E26:E27) -> #DIV/0! | F51: =SUM(F19:F21)/SUM(F26:F27) -> #DIV/0! | G51: =SUM(G19:G21)/SUM(G26:G27) -> #DIV/0! | H51: =SUM(H19:H21)/SUM(H26:H27) -> #DIV/0! | I51: =SUM(I19:I21)/SUM(I26:I27) -> #DIV/0! | J51: =SUM(J19:J21)/SUM(J26:J27) -> #DIV/0!
B52: Efficiency | C52: Inventory Turns | D52: =ABS(D5)/D37 -> #DIV/0! | E52: =ABS(E5)/E37 -> #DIV/0! | F52: =ABS(F5)/F37 -> #DIV/0! | G52: =ABS(G5)/G37 -> #DIV/0! | H52: =ABS(H5)/H37 -> #DIV/0! | I52: =ABS(I5)/I37 -> #DIV/0! | J52: =ABS(J5)/J37 -> #DIV/0!
C53: Days in Inventory | D53: =D37/(ABS(D5)/360) -> #DIV/0! | E53: =E37/(ABS(E5)/360) -> #DIV/0! | F53: =F37/(ABS(F5)/360) -> #DIV/0! | G53: =G37/(ABS(G5)/360) -> #DIV/0! | H53: =H37/(ABS(H5)/360) -> #DIV/0! | I53: =I37/(ABS(I5)/360) -> #DIV/0! | J53: =J37/(ABS(J5)/360) -> #DIV/0!
C54: Days Payables Outstanding | D54: =D26/(ABS(D5)/360) -> #DIV/0! | E54: =E26/(ABS(E5)/360) -> #DIV/0! | F54: =F26/(ABS(F5)/360) -> #DIV/0! | G54: =G26/(ABS(G5)/360) -> #DIV/0! | H54: =H26/(ABS(H5)/360) -> #DIV/0! | I54: =I26/(ABS(I5)/360) -> #DIV/0! | J54: =J26/(ABS(J5)/360) -> #DIV/0!
C55: Days Sales Outstanding | D55: =D21/(D4/360) -> #DIV/0! | E55: =E21/(E4/360) -> #DIV/0! | F55: =F21/(F4/360) -> #DIV/0! | G55: =G21/(G4/360) -> #DIV/0! | H55: =H21/(H4/360) -> #DIV/0! | I55: =I21/(I4/360) -> #DIV/0! | J55: =J21/(J4/360) -> #DIV/0!
C56: PPE Turnover | D56: =D4/SUM(D23:D24) -> #DIV/0! | E56: =E4/SUM(E23:E24) -> #DIV/0! | F56: =F4/SUM(F23:F24) -> #DIV/0! | G56: =G4/SUM(G23:G24) -> #DIV/0! | H56: =H4/SUM(H23:H24) -> #DIV/0! | I56: =I4/SUM(I23:I24) -> #DIV/0! | J56: =J4/SUM(J23:J24) -> #DIV/0!
C57: Total Asset Turnover | D57: =D4/D25 -> #DIV/0! | E57: =E4/E25 -> #DIV/0! | F57: =F4/F25 -> #DIV/0! | G57: =G4/G25 -> #DIV/0! | H57: =H4/H25 -> #DIV/0! | I57: =I4/I25 -> #DIV/0! | J57: =J4/J25 -> #DIV/0!
C58: Cash Conversion Cycle | D58: =D53+D55-D54 -> #DIV/0! | E58: =E53+E55-E54 -> #DIV/0! | F58: =F53+F55-F54 -> #DIV/0! | G58: =G53+G55-G54 -> #DIV/0! | H58: =H53+H55-H54 -> #DIV/0! | I58: =I53+I55-I54 -> #DIV/0! | J58: =J53+J55-J54 -> #DIV/0!
B59: Other | C59: Free Cash Flow (M) | D59: =SUM(D39:D40) -> 0 | E59: =SUM(E39:E40) -> 0 | F59: =SUM(F39:F40) -> 0 | G59: =SUM(G39:G40) -> 0 | H59: =SUM(H39:H40) -> 0 | I59: =SUM(I39:I40) -> 0 | J59: =SUM(J39:J40) -> 0

Sheet Year 7
B3: Income Statement | C3: MILLIONS | D3: FIRM A | E3: FIRM B | F3: FIRM C | G3: FIRM D | H3: FIRM E | I3: FIRM F | J3: FIRM G
C4: Sales
C5: Cost of Goods Sold
C6: Gross Margin
C7: Marketing
C8: Research and Development
C9: General and Administrative
C10: Income from Operations
C11: Interest Income
C12: Interest Expense
C13: Extraordinary Items
C14: Income before Tax
C15: Less Tax @ 35%
... C17: Dividends Paid
B18: Balance Sheet | C18: MILLIONS | D18: FIRM A | E18: FIRM B | F18: FIRM C | G18: FIRM D | H18: FIRM E | I18: FIRM F | J18: FIRM G
B19: Assets | C19: Cash
C20: Short-term securities
C21: Receivables
C22: Inventory
C23: Plant and Equipment
C24: Accumulated Depreciation
C25: Total Assets
B26: Liabilities | C26: Accounts Payable
C27: Short Term Debt
C28: Long Term Debt
C29: Total Liabilities
B30: Equity | C30: Stock ($1 par)
C31: Add'l Paid in Cap.
C32: Retained Earnings
C33: Treasury Stock
C34: Total Equity
B35: Inventory Detail | C35: Beg. Inventory
C36: End. Inventory
C37: Avg. Inventory | D37: =SUM(D35:D36)/2 -> 0 | E37: =SUM(E35:E36)/2 -> 0 | F37: =SUM(F35:F36)/2 -> 0 | G37: =SUM(G35:G36)/2 -> 0 | H37: =SUM(H35:H36)/2 -> 0 | I37: =SUM(I35:I36)/2 -> 0 | J37: =SUM(J35:J36)/2 -> 0
B38: Cash Flow | C38: MILLIONS | D38: FIRM A | E38: FIRM B | F38: FIRM C | G38: FIRM D | H38: FIRM E | I38: FIRM F | J38: FIRM G
C39: Net Cash from Operations
C40: Net investment
B41: Ratios | D41: FIRM A | E41: FIRM B | F41: FIRM C | G41: FIRM D | H41: FIRM E | I41: FIRM F | J41: FIRM G
B42: Profitability | C42: Gross Profit Margin | D42: =D6/D4 -> #DIV/0! | E42: =E6/E4 -> #DIV/0! | F42: =F6/F4 -> #DIV/0! | G42: =G6/G4 -> #DIV/0! | H42: =H6/H4 -> #DIV/0! | I42: =I6/I4 -> #DIV/0! | J42: =J6/J4 -> #DIV/0!
C43: Operating Profit Margin | D43: =D10/D4 -> #DIV/0! | E43: =E10/E4 -> #DIV/0! | F43: =F10/F4 -> #DIV/0! | G43: =G10/G4 -> #DIV/0! | H43: =H10/H4 -> #DIV/0! | I43: =I10/I4 -> #DIV/0! | J43: =J10/J4 -> #DIV/0!
C44: Net Profit Margin | D44: =D16/D4 -> #DIV/0! | E44: =E16/E4 -> #DIV/0! | F44: =F16/F4 -> #DIV/0! | G44: =G16/G4 -> #DIV/0! | H44: =H16/H4 -> #DIV/0! | I44: =I16/I4 -> #DIV/0! | J44: =J16/J4 -> #DIV/0!
C45: Return on Assets | D45: =D16/D25 -> #DIV/0! | E45: =E16/E25 -> #DIV/0! | F45: =F16/F25 -> #DIV/0! | G45: =G16/G25 -> #DIV/0! | H45: =H16/H25 -> #DIV/0! | I45: =I16/I25 -> #DIV/0! | J45: =J16/J25 -> #DIV/0!
C46: Return on Equity | D46: =IF(D34<0,"N/A",D16/D34) -> #DIV/0! | E46: =IF(E34<0,"N/A",E16/E34) -> #DIV/0! | F46: =IF(F34<0,"N/A",F16/F34) -> #DIV/0! | G46: =IF(G34<0,"N/A",G16/G34) -> #DIV/0! | H46: =IF(H34<0,"N/A",H16/H34) -> #DIV/0! | I46: =IF(I34<0,"N/A",I16/I34) -> #DIV/0! | J46: =IF(J34<0,"N/A",J16/J34) -> #DIV/0!
B47: Leverage | C47: Debt-to-Equity | D47: =D29/D34 -> #DIV/0! | E47: =E29/E34 -> #DIV/0! | F47: =F29/F34 -> #DIV/0! | G47: =G29/G34 -> #DIV/0! | H47: =H29/H34 -> #DIV/0! | I47: =I29/I34 -> #DIV/0! | J47: =J29/J34 -> #DIV/0!
C48: Equity Multiplier | D48: =D25/D34 -> #DIV/0! | E48: =E25/E34 -> #DIV/0! | F48: =F25/F34 -> #DIV/0! | G48: =G25/G34 -> #DIV/0! | H48: =H25/H34 -> #DIV/0! | I48: =I25/I34 -> #DIV/0! | J48: =J25/J34 -> #DIV/0!
C49: Interest Coverage | D49: =D10/ABS(D12) -> #DIV/0! | E49: =E10/ABS(E12) -> #DIV/0! | F49: =F10/ABS(F12) -> #DIV/0! | G49: =G10/ABS(G12) -> #DIV/0! | H49: =H10/ABS(H12) -> #DIV/0! | I49: =I10/ABS(I12) -> #DIV/0! | J49: =J10/ABS(J12) -> #DIV/0!
B50: Liquidity | C50: Current Ratio | D50: =SUM(D19:D22)/SUM(D26:D27) -> #DIV/0! | E50: =SUM(E19:E22)/SUM(E26:E27) -> #DIV/0! | F50: =SUM(F19:F22)/SUM(F26:F27) -> #DIV/0! | G50: =SUM(G19:G22)/SUM(G26:G27) -> #DIV/0! | H50: =SUM(H19:H22)/SUM(H26:H27) -> #DIV/0! | I50: =SUM(I19:I22)/SUM(I26:I27) -> #DIV/0! | J50: =SUM(J19:J22)/SUM(J26:J27) -> #DIV/0!
C51: Quick Ratio | D51: =SUM(D19:D21)/SUM(D26:D27) -> #DIV/0! | E51: =SUM(E19:E21)/SUM(E26:E27) -> #DIV/0! | F51: =SUM(F19:F21)/SUM(F26:F27) -> #DIV/0! | G51: =SUM(G19:G21)/SUM(G26:G27) -> #DIV/0! | H51: =SUM(H19:H21)/SUM(H26:H27) -> #DIV/0! | I51: =SUM(I19:I21)/SUM(I26:I27) -> #DIV/0! | J51: =SUM(J19:J21)/SUM(J26:J27) -> #DIV/0!
B52: Efficiency | C52: Inventory Turns | D52: =ABS(D5)/D37 -> #DIV/0! | E52: =ABS(E5)/E37 -> #DIV/0! | F52: =ABS(F5)/F37 -> #DIV/0! | G52: =ABS(G5)/G37 -> #DIV/0! | H52: =ABS(H5)/H37 -> #DIV/0! | I52: =ABS(I5)/I37 -> #DIV/0! | J52: =ABS(J5)/J37 -> #DIV/0!
C53: Days in Inventory | D53: =D37/(ABS(D5)/360) -> #DIV/0! | E53: =E37/(ABS(E5)/360) -> #DIV/0! | F53: =F37/(ABS(F5)/360) -> #DIV/0! | G53: =G37/(ABS(G5)/360) -> #DIV/0! | H53: =H37/(ABS(H5)/360) -> #DIV/0! | I53: =I37/(ABS(I5)/360) -> #DIV/0! | J53: =J37/(ABS(J5)/360) -> #DIV/0!
C54: Days Payables Outstanding | D54: =D26/(ABS(D5)/360) -> #DIV/0! | E54: =E26/(ABS(E5)/360) -> #DIV/0! | F54: =F26/(ABS(F5)/360) -> #DIV/0! | G54: =G26/(ABS(G5)/360) -> #DIV/0! | H54: =H26/(ABS(H5)/360) -> #DIV/0! | I54: =I26/(ABS(I5)/360) -> #DIV/0! | J54: =J26/(ABS(J5)/360) -> #DIV/0!
C55: Days Sales Outstanding | D55: =D21/(D4/360) -> #DIV/0! | E55: =E21/(E4/360) -> #DIV/0! | F55: =F21/(F4/360) -> #DIV/0! | G55: =G21/(G4/360) -> #DIV/0! | H55: =H21/(H4/360) -> #DIV/0! | I55: =I21/(I4/360) -> #DIV/0! | J55: =J21/(J4/360) -> #DIV/0!
C56: PPE Turnover | D56: =D4/SUM(D23:D24) -> #DIV/0! | E56: =E4/SUM(E23:E24) -> #DIV/0! | F56: =F4/SUM(F23:F24) -> #DIV/0! | G56: =G4/SUM(G23:G24) -> #DIV/0! | H56: =H4/SUM(H23:H24) -> #DIV/0! | I56: =I4/SUM(I23:I24) -> #DIV/0! | J56: =J4/SUM(J23:J24) -> #DIV/0!
C57: Total Asset Turnover | D57: =D4/D25 -> #DIV/0! | E57: =E4/E25 -> #DIV/0! | F57: =F4/F25 -> #DIV/0! | G57: =G4/G25 -> #DIV/0! | H57: =H4/H25 -> #DIV/0! | I57: =I4/I25 -> #DIV/0! | J57: =J4/J25 -> #DIV/0!
C58: Cash Conversion Cycle | D58: =D53+D55-D54 -> #DIV/0! | E58: =E53+E55-E54 -> #DIV/0! | F58: =F53+F55-F54 -> #DIV/0! | G58: =G53+G55-G54 -> #DIV/0! | H58: =H53+H55-H54 -> #DIV/0! | I58: =I53+I55-I54 -> #DIV/0! | J58: =J53+J55-J54 -> #DIV/0!
B59: Other | C59: Free Cash Flow (M) | D59: =SUM(D39:D40) -> 0 | E59: =SUM(E39:E40) -> 0 | F59: =SUM(F39:F40) -> 0 | G59: =SUM(G39:G40) -> 0 | H59: =SUM(H39:H40) -> 0 | I59: =SUM(I39:I40) -> 0 | J59: =SUM(J39:J40) -> 0

Sheet Year 8
B3: Income Statement | C3: MILLIONS | D3: FIRM A | E3: FIRM B | F3: FIRM C | G3: FIRM D | H3: FIRM E | I3: FIRM F | J3: FIRM G
C4: Sales
C5: Cost of Goods Sold
C6: Gross Margin
C7: Marketing
C8: Research and Development
C9: General and Administrative
C10: Income from Operations
C11: Interest Income
C12: Interest Expense
C13: Extraordinary Items
C14: Income before Tax
C15: Less Tax @ 35%
... C17: Dividends Paid
B18: Balance Sheet | C18: MILLIONS | D18: FIRM A | E18: FIRM B | F18: FIRM C | G18: FIRM D | H18: FIRM E | I18: FIRM F | J18: FIRM G
B19: Assets | C19: Cash
C20: Short-term securities
C21: Receivables
C22: Inventory
C23: Plant and Equipment
C24: Accumulated Depreciation
C25: Total Assets
B26: Liabilities | C26: Accounts Payable
C27: Short Term Debt
C28: Long Term Debt
C29: Total Liabilities
B30: Equity | C30: Stock ($1 par)
C31: Add'l Paid in Cap.
C32: Retained Earnings
C33: Treasury Stock
C34: Total Equity
B35: Inventory Detail | C35: Beg. Inventory
C36: End. Inventory
C37: Avg. Inventory | D37: =SUM(D35:D36)/2 -> 0 | E37: =SUM(E35:E36)/2 -> 0 | F37: =SUM(F35:F36)/2 -> 0 | G37: =SUM(G35:G36)/2 -> 0 | H37: =SUM(H35:H36)/2 -> 0 | I37: =SUM(I35:I36)/2 -> 0 | J37: =SUM(J35:J36)/2 -> 0
B38: Cash Flow | C38: MILLIONS | D38: FIRM A | E38: FIRM B | F38: FIRM C | G38: FIRM D | H38: FIRM E | I38: FIRM F | J38: FIRM G
C39: Net Cash from Operations
C40: Net investment
B41: Ratios | D41: FIRM A | E41: FIRM B | F41: FIRM C | G41: FIRM D | H41: FIRM E | I41: FIRM F | J41: FIRM G
B42: Profitability | C42: Gross Profit Margin | D42: =D6/D4 -> #DIV/0! | E42: =E6/E4 -> #DIV/0! | F42: =F6/F4 -> #DIV/0! | G42: =G6/G4 -> #DIV/0! | H42: =H6/H4 -> #DIV/0! | I42: =I6/I4 -> #DIV/0! | J42: =J6/J4 -> #DIV/0!
C43: Operating Profit Margin | D43: =D10/D4 -> #DIV/0! | E43: =E10/E4 -> #DIV/0! | F43: =F10/F4 -> #DIV/0! | G43: =G10/G4 -> #DIV/0! | H43: =H10/H4 -> #DIV/0! | I43: =I10/I4 -> #DIV/0! | J43: =J10/J4 -> #DIV/0!
C44: Net Profit Margin | D44: =D16/D4 -> #DIV/0! | E44: =E16/E4 -> #DIV/0! | F44: =F16/F4 -> #DIV/0! | G44: =G16/G4 -> #DIV/0! | H44: =H16/H4 -> #DIV/0! | I44: =I16/I4 -> #DIV/0! | J44: =J16/J4 -> #DIV/0!
C45: Return on Assets | D45: =D16/D25 -> #DIV/0! | E45: =E16/E25 -> #DIV/0! | F45: =F16/F25 -> #DIV/0! | G45: =G16/G25 -> #DIV/0! | H45: =H16/H25 -> #DIV/0! | I45: =I16/I25 -> #DIV/0! | J45: =J16/J25 -> #DIV/0!
C46: Return on Equity | D46: =IF(D34<0,"N/A",D16/D34) -> #DIV/0! | E46: =IF(E34<0,"N/A",E16/E34) -> #DIV/0! | F46: =IF(F34<0,"N/A",F16/F34) -> #DIV/0! | G46: =IF(G34<0,"N/A",G16/G34) -> #DIV/0! | H46: =IF(H34<0,"N/A",H16/H34) -> #DIV/0! | I46: =IF(I34<0,"N/A",I16/I34) -> #DIV/0! | J46: =IF(J34<0,"N/A",J16/J34) -> #DIV/0!
B47: Leverage | C47: Debt-to-Equity | D47: =D29/D34 -> #DIV/0! | E47: =E29/E34 -> #DIV/0! | F47: =F29/F34 -> #DIV/0! | G47: =G29/G34 -> #DIV/0! | H47: =H29/H34 -> #DIV/0! | I47: =I29/I34 -> #DIV/0! | J47: =J29/J34 -> #DIV/0!
C48: Equity Multiplier | D48: =D25/D34 -> #DIV/0! | E48: =E25/E34 -> #DIV/0! | F48: =F25/F34 -> #DIV/0! | G48: =G25/G34 -> #DIV/0! | H48: =H25/H34 -> #DIV/0! | I48: =I25/I34 -> #DIV/0! | J48: =J25/J34 -> #DIV/0!
C49: Interest Coverage | D49: =D10/ABS(D12) -> #DIV/0! | E49: =E10/ABS(E12) -> #DIV/0! | F49: =F10/ABS(F12) -> #DIV/0! | G49: =G10/ABS(G12) -> #DIV/0! | H49: =H10/ABS(H12) -> #DIV/0! | I49: =I10/ABS(I12) -> #DIV/0! | J49: =J10/ABS(J12) -> #DIV/0!
B50: Liquidity | C50: Current Ratio | D50: =SUM(D19:D22)/SUM(D26:D27) -> #DIV/0! | E50: =SUM(E19:E22)/SUM(E26:E27) -> #DIV/0! | F50: =SUM(F19:F22)/SUM(F26:F27) -> #DIV/0! | G50: =SUM(G19:G22)/SUM(G26:G27) -> #DIV/0! | H50: =SUM(H19:H22)/SUM(H26:H27) -> #DIV/0! | I50: =SUM(I19:I22)/SUM(I26:I27) -> #DIV/0! | J50: =SUM(J19:J22)/SUM(J26:J27) -> #DIV/0!
C51: Quick Ratio | D51: =SUM(D19:D21)/SUM(D26:D27) -> #DIV/0! | E51: =SUM(E19:E21)/SUM(E26:E27) -> #DIV/0! | F51: =SUM(F19:F21)/SUM(F26:F27) -> #DIV/0! | G51: =SUM(G19:G21)/SUM(G26:G27) -> #DIV/0! | H51: =SUM(H19:H21)/SUM(H26:H27) -> #DIV/0! | I51: =SUM(I19:I21)/SUM(I26:I27) -> #DIV/0! | J51: =SUM(J19:J21)/SUM(J26:J27) -> #DIV/0!
B52: Efficiency | C52: Inventory Turns | D52: =ABS(D5)/D37 -> #DIV/0! | E52: =ABS(E5)/E37 -> #DIV/0! | F52: =ABS(F5)/F37 -> #DIV/0! | G52: =ABS(G5)/G37 -> #DIV/0! | H52: =ABS(H5)/H37 -> #DIV/0! | I52: =ABS(I5)/I37 -> #DIV/0! | J52: =ABS(J5)/J37 -> #DIV/0!
C53: Days in Inventory | D53: =D37/(ABS(D5)/360) -> #DIV/0! | E53: =E37/(ABS(E5)/360) -> #DIV/0! | F53: =F37/(ABS(F5)/360) -> #DIV/0! | G53: =G37/(ABS(G5)/360) -> #DIV/0! | H53: =H37/(ABS(H5)/360) -> #DIV/0! | I53: =I37/(ABS(I5)/360) -> #DIV/0! | J53: =J37/(ABS(J5)/360) -> #DIV/0!
C54: Days Payables Outstanding | D54: =D26/(ABS(D5)/360) -> #DIV/0! | E54: =E26/(ABS(E5)/360) -> #DIV/0! | F54: =F26/(ABS(F5)/360) -> #DIV/0! | G54: =G26/(ABS(G5)/360) -> #DIV/0! | H54: =H26/(ABS(H5)/360) -> #DIV/0! | I54: =I26/(ABS(I5)/360) -> #DIV/0! | J54: =J26/(ABS(J5)/360) -> #DIV/0!
C55: Days Sales Outstanding | D55: =D21/(D4/360) -> #DIV/0! | E55: =E21/(E4/360) -> #DIV/0! | F55: =F21/(F4/360) -> #DIV/0! | G55: =G21/(G4/360) -> #DIV/0! | H55: =H21/(H4/360) -> #DIV/0! | I55: =I21/(I4/360) -> #DIV/0! | J55: =J21/(J4/360) -> #DIV/0!
C56: PPE Turnover | D56: =D4/SUM(D23:D24) -> #DIV/0! | E56: =E4/SUM(E23:E24) -> #DIV/0! | F56: =F4/SUM(F23:F24) -> #DIV/0! | G56: =G4/SUM(G23:G24) -> #DIV/0! | H56: =H4/SUM(H23:H24) -> #DIV/0! | I56: =I4/SUM(I23:I24) -> #DIV/0! | J56: =J4/SUM(J23:J24) -> #DIV/0!
C57: Total Asset Turnover | D57: =D4/D25 -> #DIV/0! | E57: =E4/E25 -> #DIV/0! | F57: =F4/F25 -> #DIV/0! | G57: =G4/G25 -> #DIV/0! | H57: =H4/H25 -> #DIV/0! | I57: =I4/I25 -> #DIV/0! | J57: =J4/J25 -> #DIV/0!
C58: Cash Conversion Cycle | D58: =D53+D55-D54 -> #DIV/0! | E58: =E53+E55-E54 -> #DIV/0! | F58: =F53+F55-F54 -> #DIV/0! | G58: =G53+G55-G54 -> #DIV/0! | H58: =H53+H55-H54 -> #DIV/0! | I58: =I53+I55-I54 -> #DIV/0! | J58: =J53+J55-J54 -> #DIV/0!
B59: Other | C59: Free Cash Flow (M) | D59: =SUM(D39:D40) -> 0 | E59: =SUM(E39:E40) -> 0 | F59: =SUM(F39:F40) -> 0 | G59: =SUM(G39:G40) -> 0 | H59: =SUM(H39:H40) -> 0 | I59: =SUM(I39:I40) -> 0 | J59: =SUM(J39:J40) -> 0
